GramDB/__init__.py
GramDB/asyncio.py
GramDB/exception.py
GramDB/helper.py
GramDB/main.py
GramDB/method.py
GramDB-2.2.0.dist-info/LICENSE
GramDB-2.2.0.dist-info/METADATA
GramDB-2.2.0.dist-info/WHEEL
GramDB-2.2.0.dist-info/top_level.txt
GramDB-2.2.0.dist-info/RECORD
