Metadata-Version: 2.1
Name: GramDB
Version: 2.2.0
Summary: Unlimited Capacity Database For Programming Using Telegram as Database.
Home-page: https://github.com/ishikki-akabane/GramDB
Download-URL: https://github.com/ishikki-akabane/GramDB/releases/latest
Author: ishikki-Akabane
Author-email: ishikkiakabane@outlook.com
License: GNU General Public License v3.0
Keywords: telegram,db,database,free,storage,code
Classifier: Framework :: AsyncIO
Classifier: Development Status :: 3 - Alpha
Classifier: Intended Audience :: Developers
Classifier: License :: OSI Approved :: GNU General Public License v2 or later (GPLv2+)
Classifier: Natural Language :: English
Classifier: Operating System :: OS Independent
Classifier: Programming Language :: Python :: 3.7
Classifier: Programming Language :: Python :: 3.8
Classifier: Programming Language :: Python :: 3.9
Classifier: Programming Language :: Python :: 3.10
Classifier: Topic :: Internet :: WWW/HTTP
Classifier: Topic :: Software Development :: Libraries
Classifier: Topic :: Software Development :: Build Tools
License-File: LICENSE
Requires-Dist: requests
Requires-Dist: aiohttp
Requires-Dist: asyncio
